quantpanda/__init__.py
QuantPanda-0.0.27.dist-info/LICENCE.txt
QuantPanda-0.0.27.dist-info/METADATA
QuantPanda-0.0.27.dist-info/WHEEL
QuantPanda-0.0.27.dist-info/top_level.txt
QuantPanda-0.0.27.dist-info/RECORD
