Metadata-Version: 2.1
Name: QuantPanda
Version: 0.0.27
Summary: Backtesting Engine
Home-page: UNKNOWN
Author: Ashish Ongari
Author-email: ashishongari@gmail.com
License: MIT
Keywords: backtesting,quant,algotrading,systematictrading,trading
Platform: UNKNOWN
Classifier: Development Status :: 5 - Production/Stable
Classifier: Intended Audience :: Education
Classifier: Operating System :: Microsoft :: Windows :: Windows 10
Classifier: License :: OSI Approved :: MIT License
Classifier: Programming Language :: Python :: 3
License-File: LICENCE.txt
Requires-Dist: pandas-ta
Requires-Dist: pandas
Requires-Dist: numpy
Requires-Dist: boto3
